week4/reference/systolic_array/input_skew.v
// input_skew.v — Activation staircase delay buffer
//
// 역할:
//   - ROWS 개 입력 중 row i 를 i cycle 지연시켜 출력
//   - systolic array 의 wave 정렬 (모든 K-index 데이터가 동시에 PE 에 도착)
//
// 동작 (예: ROWS=3):
//   cycle 0:  in[0]=a, in[1]=b, in[2]=c  →  out[0]=a, out[1]=?, out[2]=?
//   cycle 1:  in[0]=d, in[1]=e, in[2]=f  →  out[0]=d, out[1]=b, out[2]=?
//   cycle 2:  in[0]=g, in[1]=h, in[2]=i  →  out[0]=g, out[1]=e, out[2]=c
//
// 구현:
//   - row i 는 길이 i 의 shift register
//   - row 0 은 pass-through (delay 0)

module input_skew #(
    parameter ROWS = 4,
    parameter DATA_WIDTH = 8
) (
    input  wire clk,
    input  wire rst_n,
    input  wire en,
    input  wire signed [ROWS*DATA_WIDTH-1:0] act_in_flat,
    output wire signed [ROWS*DATA_WIDTH-1:0] act_out_flat
);

    genvar i, k;

    generate
        for (i = 0; i < ROWS; i = i + 1) begin : g_row
            if (i == 0) begin : g_passthrough
                // row 0 : pass-through (delay 0)
                assign act_out_flat[(i+1)*DATA_WIDTH-1 -: DATA_WIDTH]
                     = act_in_flat[(i+1)*DATA_WIDTH-1 -: DATA_WIDTH];
            end else begin : g_delay
                // row i : i-stage shift register → pe_array (edge-BEFORE-NBA read) 기준 i 사이클 지연
                // (cocotb read = AFTER NBA 는 i-1 사이클 지연으로 보임)
                reg signed [DATA_WIDTH-1:0] pipe [0:i-1];
                integer m;

                always @(posedge clk or negedge rst_n) begin
                    if (!rst_n) begin
                        for (m = 0; m < i; m = m + 1) pipe[m] <= {DATA_WIDTH{1'b0}};
                    end else if (en) begin
                        pipe[0] <= act_in_flat[(i+1)*DATA_WIDTH-1 -: DATA_WIDTH];
                        for (m = 1; m < i; m = m + 1) pipe[m] <= pipe[m-1];
                    end
                end

                assign act_out_flat[(i+1)*DATA_WIDTH-1 -: DATA_WIDTH] = pipe[i-1];
            end
        end
    endgenerate

`ifndef SYNTHESIS

`ifdef DUMP_INPUT_SKEW

initial begin
    $dumpfile("input_skew.vcd");
    $dumpvars(0, input_skew);
end

`else

`ifndef NO_VCD_DUMP

initial begin
    $dumpfile("dump.vcd");
    $dumpvars(0, input_skew);
end

`endif

`endif

`endif

endmodule

week4/reference/systolic_array/dump.vcd
$date
	Mon Jul 27 18:14:51 2026
$end
$version
	Icarus Verilog
$end
$timescale
	1ps
$end
$scope module input_skew $end
$var wire 32 ! act_in_flat [31:0] $end
$var wire 1 " clk $end
$var wire 1 # en $end
$var wire 1 $ rst_n $end
$var wire 32 % act_out_flat [31:0] $end
$var parameter 32 & DATA_WIDTH $end
$var parameter 32 ' ROWS $end
$scope begin g_row[0] $end
$var parameter 2 ( i $end
$scope begin g_passthrough $end
$upscope $end
$upscope $end
$scope begin g_row[1] $end
$var parameter 2 ) i $end
$scope begin g_delay $end
$var integer 32 * m [31:0] $end
$upscope $end
$upscope $end
$scope begin g_row[2] $end
$var parameter 3 + i $end
$scope begin g_delay $end
$var integer 32 , m [31:0] $end
$upscope $end
$upscope $end
$scope begin g_row[3] $end
$var parameter 3 - i $end
$scope begin g_delay $end
$var integer 32 . m [31:0] $end
$upscope $end
$upscope $end
$upscope $end
$enddefinitions $end
$comment Show the parameter values. $end
$dumpall
b11 -
b10 +
b1 )
b0 (
b100 '
b1000 &
$end
#0
$dumpvars
b11 .
b10 ,
b1 *
b0 %
0$
1#
1"
b0 !
$end
#5000
0"
#10000
1$
b11 .
b10 ,
b1 *
1"
#15000
0"
#20000
b10 ,
b11 .
1"
#25000
b1 %
0"
b1000000010000000100000001 !
#30000
b100000001 %
b11 .
b10 ,
1"
#35000
b100000010 %
0"
b10000000100000001000000010 !
#40000
b10000001000000010 %
b10 ,
b11 .
1"
#45000
b10000001000000011 %
0"
b11000000110000001100000011 !
#50000
b1000000100000001100000011 %
b11 .
b10 ,
1"
#55000
b1000000100000001100000100 %
0"
b100000001000000010000000100 !
#60000
b10000000110000010000000100 %
b10 ,
b11 .
1"
#65000
b10000000110000010000000101 %
0"
b101000001010000010100000101 !
#70000
b11000001000000010100000101 %
b11 .
b10 ,
1"
#75000
b11000001000000010100000110 %
0"
b110000001100000011000000110 !
#80000
b100000001010000011000000110 %
b10 ,
b11 .
1"
#85000
b100000001010000011000000111 %
0"
b111000001110000011100000111 !
#90000
b101000001100000011100000111 %
b11 .
b10 ,
1"
#95000
b101000001100000011100001000 %
0"
b1000000010000000100000001000 !
#100000
b110000001110000100000001000 %
b10 ,
b11 .
1"
#105001
b0 %
b11 .
b10 ,
b1 *
0$
b0 !
#110001
0"
#115001
b1 *
b10 ,
b11 .
1"
#120001
0"
#125001
1$
b11 .
b10 ,
b1 *
1"
#130001
0"
#135001
b10 ,
b11 .
1"
#140001
b1100011 %
0"
b1100011011000110110001101100011 !
#145001
b110001101100011 %
b11 .
b10 ,
1"
#150001
b110001100000000 %
0"
b0 !
#155001
b11000110000000000000000 %
b10 ,
b11 .
1"
#160001
0"
#165001
b1100011000000000000000000000000 %
b11 .
b10 ,
1"
#170001
0"
#175001
b0 %
b10 ,
b11 .
1"
#180001
0"
#185001
b11 .
b10 ,
1"
#190001
0"
#195001
b10 ,
b11 .
1"
#200002
b11 .
b10 ,
b1 *
0$
#205002
0"
#210002
b1 *
b10 ,
b11 .
1"
#215002
0"
#220002
1$
b11 .
b10 ,
b1 *
1"
#225002
0"
#230002
b10 ,
b11 .
1"
#235002
b1 %
0"
b1000000010000000100000001 !
#240002
b100000001 %
b11 .
b10 ,
1"
#245002
b100000010 %
0"
b10000000100000001000000010 !
#250002
b10000001000000010 %
b10 ,
b11 .
1"
#255002
b10000001000000011 %
0"
b11000000110000001100000011 !
#260002
b1000000100000001100000011 %
b11 .
b10 ,
1"
#265002
b1000000100000001100000100 %
0"
b100000001000000010000000100 !
#270002
b10000000110000010000000100 %
b10 ,
b11 .
1"
#275002
b10000000110000010001100011 %
0"
b1100011011000110110001101100011 !
0#
